tuyadatac/__init__.py
tuyadatac/client_ftp.py
tuyadatac/client_workspace.py
tuyadatac/client_workspace_test.py
tuyadatac-0.0.3.dist-info/LICENSE
tuyadatac-0.0.3.dist-info/METADATA
tuyadatac-0.0.3.dist-info/WHEEL
tuyadatac-0.0.3.dist-info/top_level.txt
tuyadatac-0.0.3.dist-info/RECORD
